README.rst
setup.py
valid_email/__init__.py
valid_email/valid_email.py
valid_email.egg-info/PKG-INFO
valid_email.egg-info/SOURCES.txt
valid_email.egg-info/dependency_links.txt
valid_email.egg-info/not-zip-safe
valid_email.egg-info/top_level.txt