Metadata-Version: 1.0
Name: valid-email
Version: 0.4
Summary: Package to find a valid email id.
Home-page: https://github.com/hmnhGeek/valid_email
Author: Himanshu Sharma
Author-email: hmnhsharma97@gmail.com
License: MIT
Platform: UNKNOWN
